CHANGELOG.txt
LICENCE.txt
MANIFEST.in
README.md
__init__.py
setup.py
forcer.egg-info/PKG-INFO
forcer.egg-info/SOURCES.txt
forcer.egg-info/dependency_links.txt
forcer.egg-info/requires.txt
forcer.egg-info/top_level.txt
lib/guess_password_by.py
lib/ssh_authentication.py
tests/__init__.py
tests/test_guess_password_by.py
tests/test_ssh_authentication.py
tests/test_utils/test_dictionary.py
utils/__init__.py
utils/dictionary.py