Metadata-Version: 2.1
Name: forcer
Version: 0.0.1
Summary: A library to use Brute Force methods
Home-page: https://github.com/ju-dev-16
Author: Jahid Uddin
Author-email: jahidudd65@gmail.com
License: MIT
Keywords: brute force passwords dictionary ssh login
Platform: UNKNOWN
Classifier: Development Status :: 5 - Production/Stable
Classifier: Intended Audience :: Education
Classifier: Operating System :: Microsoft :: Windows :: Windows 10
Classifier: License :: OSI Approved :: MIT License
Classifier: Programming Language :: Python :: 3
License-File: LICENCE.txt
